solarcalc.py
solarcalc-1.1.data/data/demo_climatedata.csv
solarcalc-1.1.dist-info/LICENSE
solarcalc-1.1.dist-info/METADATA
solarcalc-1.1.dist-info/WHEEL
solarcalc-1.1.dist-info/top_level.txt
solarcalc-1.1.dist-info/RECORD
