Metadata-Version: 2.1
Name: solarcalc
Version: 1.1
Summary: Hourly global solar radiation estimator.
Home-page: https://github.com/cgq-qgc/solarcalc
Author: Jean-Sébastien Gosselin
Author-email: jean-sebastien.gosselin@outlook.ca
License: MIT
Platform: UNKNOWN
Classifier: Programming Language :: Python :: 3
Classifier: License :: OSI Approved :: MIT License
Classifier: Operating System :: OS Independent
Classifier: Intended Audience :: Science/Research
Classifier: Intended Audience :: Education
Classifier: Topic :: Scientific/Engineering
Requires-Dist: numpy
Requires-Dist: pandas
